kala/__init__.py
kala/models/__init__.py
kala/models/agents.py
kala/models/data.py
kala/models/game.py
kala/models/graphs.py
kala/models/memory.py
kala/models/shocks.py
kala/models/strategies.py
kala/settings/__init__.py
kala/settings/consts.py
kala/utils/__init__.py
kala/utils/game_stats.py
kala/utils/wrappers.py
kala/utils/io/__init__.py
kala/utils/io/netz.py
kala_econ_games-1.0.0.dist-info/METADATA
kala_econ_games-1.0.0.dist-info/WHEEL
kala_econ_games-1.0.0.dist-info/licenses/LICENSE
kala_econ_games-1.0.0.dist-info/RECORD
