Metadata-Version: 2.4
Name: kala-econ-games
Version: 1.0.0
Summary: Kala: agent-based econ games
Author-email: "Rodrigo L.C." <rodrigolealc@ciencias.unam.mx>
License: MIT
License-File: LICENSE
Requires-Python: >=3.10
Requires-Dist: mkdocs>=1.5.3
Requires-Dist: networkx
Requires-Dist: numpy
Requires-Dist: pendulum
Requires-Dist: pydantic>=2.9.2
Requires-Dist: scipy
Requires-Dist: statsmodels
Requires-Dist: zstandard>=0.23.0
